wrench/__init__.py
wrench/app.py
wrench/cli.py
wrench/exceptions.py
wrench/wrench.py
wrench/commands/__init__.py
wrench/commands/config.py
wrench/commands/git.py
wrench/commands/install.py
wrench/commands/make.py
wrench/commands/setup.py
wrench/commands/update.py
wrench/commands/utils.py
wrench/config/__init__.py
wrench/config/common_site_config.py
wrench/config/lets_encrypt.py
wrench/config/nginx.py
wrench/config/procfile.py
wrench/config/production_setup.py
wrench/config/redis.py
wrench/config/site_config.py
wrench/config/supervisor.py
wrench/config/systemd.py
wrench/config/templates/502.html
wrench/config/templates/Procfile
wrench/config/templates/letsencrypt.cfg
wrench/config/templates/nginx.conf
wrench/config/templates/nginx_default.conf
wrench/config/templates/redis_cache.conf
wrench/config/templates/redis_queue.conf
wrench/config/templates/saashq_sudoers
wrench/config/templates/supervisor.conf
wrench/config/templates/wrench_manager_nginx.conf
wrench/config/templates/systemd/saashq-wrench-node-socketio.service
wrench/config/templates/systemd/saashq-wrench-redis-cache.service
wrench/config/templates/systemd/saashq-wrench-redis-queue.service
wrench/config/templates/systemd/saashq-wrench-redis.target
wrench/config/templates/systemd/saashq-wrench-saashq-default-worker.service
wrench/config/templates/systemd/saashq-wrench-saashq-long-worker.service
wrench/config/templates/systemd/saashq-wrench-saashq-schedule.service
wrench/config/templates/systemd/saashq-wrench-saashq-short-worker.service
wrench/config/templates/systemd/saashq-wrench-saashq-web.service
wrench/config/templates/systemd/saashq-wrench-web.target
wrench/config/templates/systemd/saashq-wrench-workers.target
wrench/config/templates/systemd/saashq-wrench.target
wrench/patches/__init__.py
wrench/patches/patches.txt
wrench/patches/v5/__init__.py
wrench/patches/v5/fix_backup_cronjob.py
wrench/patches/v5/fix_user_permissions.py
wrench/patches/v5/set_live_reload_config.py
saashq_wrench-5.0.4.dev0.dist-info/METADATA
saashq_wrench-5.0.4.dev0.dist-info/WHEEL
saashq_wrench-5.0.4.dev0.dist-info/entry_points.txt
saashq_wrench-5.0.4.dev0.dist-info/licenses/LICENSE
saashq_wrench-5.0.4.dev0.dist-info/RECORD
